MessageBoxWin32/__init__.py
MessageBoxWin32/messagebox.py
messageboxwin32-0.1.4.dist-info/METADATA
messageboxwin32-0.1.4.dist-info/WHEEL
messageboxwin32-0.1.4.dist-info/top_level.txt
messageboxwin32-0.1.4.dist-info/RECORD
