Metadata-Version: 2.4
Name: MessageBoxWin32
Version: 0.1.4
Summary: Caixas de diálogo Windows MessageBox via ctypes (sem Tkinter, porém especificamente para Windows).
Home-page: https://github.com/lhrp/messageboxwin32
Author: Leonardo Henrique Rangon Paulino
Author-email: leonardo@lhrp.com.br
Classifier: Programming Language :: Python :: 3
Classifier: Operating System :: Microsoft :: Windows
Requires-Python: >=3.6
Requires-Dist: wxPython==4.2.3
Dynamic: author
Dynamic: author-email
Dynamic: classifier
Dynamic: description
Dynamic: description-content-type
Dynamic: home-page
Dynamic: requires-dist
Dynamic: requires-python
Dynamic: summary
